bocas/__init__.py
bocas/launch.py
bocas/result.py
bocas/run.py
bocas/sweep.py
bocas/artifacts/__init__.py
bocas/artifacts/artifact.py
bocas/artifacts/keras_history.py
bocas/artifacts/metrics.py
bocas-0.0.3.dist-info/METADATA
bocas-0.0.3.dist-info/WHEEL
bocas-0.0.3.dist-info/top_level.txt
bocas-0.0.3.dist-info/RECORD
